examples/_run_all_examples.py
examples/logo.py
examples/random_squares.py
examples/roses.py
examples/star.py
examples/transparent_colors.py
examples/yin_yang.py
gizeh/__init__.py
gizeh/geometry.py
gizeh/gizeh.py
gizeh/tools.py
gizeh-0.1.12.dist-info/licenses/LICENCE.txt
gizeh-0.1.12.dist-info/METADATA
gizeh-0.1.12.dist-info/WHEEL
gizeh-0.1.12.dist-info/top_level.txt
gizeh-0.1.12.dist-info/RECORD
