Metadata-Version: 2.4
Name: gizeh
Version: 0.1.12
Summary: Simple vector graphics in Python
Author: Zulko
License: MIT
Project-URL: Homepage, https://github.com/Zulko/gizeh
Project-URL: Repository, https://github.com/Zulko/gizeh
Project-URL: Issues, https://github.com/Zulko/gizeh/issues
Keywords: Cairo,vector,graphics
Classifier: Development Status :: 4 - Beta
Classifier: Intended Audience :: Developers
Classifier: License :: OSI Approved :: MIT License
Classifier: Programming Language :: Python :: 3
Classifier: Programming Language :: Python :: 3.7
Classifier: Programming Language :: Python :: 3.8
Classifier: Programming Language :: Python :: 3.9
Classifier: Programming Language :: Python :: 3.10
Classifier: Programming Language :: Python :: 3.11
Classifier: Programming Language :: Python :: 3.12
Classifier: Topic :: Multimedia :: Graphics
Requires-Python: >=3.7
License-File: LICENCE.txt
Requires-Dist: cairocffi
Requires-Dist: numpy
Requires-Dist: importlib-metadata>=1.0; python_version < "3.8"
Dynamic: license-file
